{
  "kind": "singleType",
  "collectionName": "request_quotes",
  "info": {
    "singularName": "request-quote",
    "pluralName": "request-quotes",
    "displayName": "request_quote"
  },
  "options": {
    "draftAndPublish": true
  },
  "pluginOptions": {
    "i18n": {
      "localized": true
    }
  },
  "attributes": {
    "label": {
      "type": "string",
      "pluginOptions": {
        "i18n": {
          "localized": true
        }
      },
      "required": true
    },
    "title": {
      "type": "string",
      "pluginOptions": {
        "i18n": {
          "localized": true
        }
      },
      "required": true
    },
    "description": {
      "type": "text",
      "pluginOptions": {
        "i18n": {
          "localized": true
        }
      },
      "required": true
    },
    "list": {
      "type": "component",
      "pluginOptions": {
        "i18n": {
          "localized": true
        }
      },
      "component": "general.icon-list",
      "repeatable": true
    },
    "form_title": {
      "type": "string",
      "pluginOptions": {
        "i18n": {
          "localized": true
        }
      },
      "required": true
    },
    "form_label": {
      "type": "component",
      "pluginOptions": {
        "i18n": {
          "localized": true
        }
      },
      "component": "general.form-label",
      "repeatable": true
    },
    "wa_text": {
      "type": "text",
      "pluginOptions": {
        "i18n": {
          "localized": true
        }
      },
      "required": true
    }
  }
}
